setup.py
custom_python_package/__init__.py
custom_python_package.egg-info/PKG-INFO
custom_python_package.egg-info/SOURCES.txt
custom_python_package.egg-info/dependency_links.txt
custom_python_package.egg-info/top_level.txt