Metadata-Version: 1.0
Name: custom-python-package
Version: 0.1
Summary: Dummy custom package
Home-page: UNKNOWN
Author: Chintan Bhatt
Author-email: UNKNOWN
License: UNKNOWN
Platform: UNKNOWN
